{
  "name": "R. Mutt",
  "osc1_kbd": true,
  "osc1_coarse": 1,
  "osc1_saw": 1,
  "osc1_sqr": 0,
  "osc1_tri": 0,
  "osc1_sin": 0.5724,
  "osc1_fm": 0.2513,
  "osc2_kbd": true,
  "osc2_coarse": 1,
  "osc2_waveform": "sawtooth",
  "osc2_detune": 0,
  "osc2_fine": 0,
  "osc2_shape": 0.8659,
  "osc2_fm": 0.0952,
  "noise_color": "white",
  "osc1_mix": 1,
  "osc2_mix": 0.4541,
  "noise_mix": 0,
  "ext_mix": 0,
  "filter_mode": "bp",
  "cutoff": 0.0872,
  "res": 1,
  "filter_eg": 0.2018,
  "filter_kbd": 0,
  "filter_attack": 0.008,
  "filter_decay": 0.1218,
  "filter_sustain": 0.2339,
  "filter_release": 0.1521,
  "vca_gain": 0,
  "vca_attack": 0.0001,
  "vca_decay": 0.0818,
  "vca_sustain": 0.3563,
  "vca_release": 0.0818,
  "lfo_shape": "sine",
  "lfo_rate": 1,
  "lfo_pitch": 45.9946,
  "lfo_filter": 4429.0492,
  "lfo_amp": 1,
  "delay_rate": 0.0577,
  "delay": 0.2043,
  "portamento_mode": "exponential",
  "portamento": 0.19,
  "mod": 1,
  "mod_direction": 1
}